geotrouvetout/__init__.py
geotrouvetout/__main__.py
geotrouvetout/area.py
geotrouvetout/color_analysis.py
geotrouvetout/combination.py
geotrouvetout/language_detection.py
geotrouvetout/object_detection.py
geotrouvetout/overpass.py
geotrouvetout/util.py
geotrouvetout-1.0.0.dist-info/LICENSE
geotrouvetout-1.0.0.dist-info/METADATA
geotrouvetout-1.0.0.dist-info/WHEEL
geotrouvetout-1.0.0.dist-info/entry_points.txt
geotrouvetout-1.0.0.dist-info/RECORD
