Metadata-Version: 2.1
Name: geotrouvetout
Version: 1.0.0
Summary: geotrouvetout gives geolocation information from an image
License: MIT
Author: David Bret
Requires-Python: >=3.10,<4.0
Classifier: License :: OSI Approved :: MIT License
Classifier: Programming Language :: Python :: 3
Classifier: Programming Language :: Python :: 3.10
Classifier: Programming Language :: Python :: 3.11
Requires-Dist: argparse (>=1.4.0,<2.0.0)
Requires-Dist: collection (>=0.1.6,<0.2.0)
Requires-Dist: coloredlogs (>=15.0.1,<16.0.0)
Requires-Dist: countryinfo (>=0.1.2,<0.2.0)
Requires-Dist: csvfile (>=3.4.0,<4.0.0)
Requires-Dist: fastapi (>=0.92.0,<0.93.0)
Requires-Dist: geopy (>=2.3.0,<3.0.0)
Requires-Dist: googlemaps (>=4.10.0,<5.0.0)
Requires-Dist: langdetect (>=1.0.9,<2.0.0)
Requires-Dist: matplotlib (>=3.7.0,<4.0.0)
Requires-Dist: nominatim (>=0.1,<0.2)
Requires-Dist: numpy (>=1.24.2,<2.0.0)
Requires-Dist: opencv-python (>=4.7.0.72,<5.0.0.0)
Requires-Dist: osmnx (>=1.3.0,<2.0.0)
Requires-Dist: overpy (>=0.6,<0.7)
Requires-Dist: pathlib (>=1.0.1,<2.0.0)
Requires-Dist: pillow (>=9.4.0,<10.0.0)
Requires-Dist: pycountry (>=22.3.5,<23.0.0)
Requires-Dist: pytesseract (>=0.3.10,<0.4.0)
Requires-Dist: python-multipart (>=0.0.5,<0.0.6)
Requires-Dist: requests (>=2.28.2,<3.0.0)
Requires-Dist: rich-argparse (>=1.1.0,<2.0.0)
Requires-Dist: scikit-image (>=0.20.0,<0.21.0)
Requires-Dist: shapely (>=2.0.1,<3.0.0)
Requires-Dist: tesseract (>=0.1.3,<0.2.0)
Requires-Dist: torch (>=1.13.1,<2.0.0)
Requires-Dist: torchvision (>=0.14.1,<0.15.0)
Requires-Dist: ultralytics (>=8.0.40,<9.0.0)
Requires-Dist: uvicorn[standard] (>=0.20.0,<0.21.0)
